pitex/__init__.py
pitex/command.py
pitex/config.py
pitex/document.py
pitex/elements.py
pitex/engine.py
pitex/package.py
pitex-1.0.1.dist-info/LICENSE.md
pitex-1.0.1.dist-info/WHEEL
pitex-1.0.1.dist-info/METADATA
pitex-1.0.1.dist-info/RECORD
