Metadata-Version: 2.1
Name: pitex
Version: 1.0.1
Summary: 
Author: girogio
Author-email: giorgiogrigolo03@gmail.com
Requires-Python: >=3.9,<4.0
Classifier: Programming Language :: Python :: 3
Classifier: Programming Language :: Python :: 3.9
Classifier: Programming Language :: Python :: 3.10
Classifier: Programming Language :: Python :: 3.11
